judge_llm/__init__.py
judge_llm/__main__.py
judge_llm/cli.py
judge_llm/core/__init__.py
judge_llm/core/config_loader.py
judge_llm/core/config_merger.py
judge_llm/core/config_validator.py
judge_llm/core/evaluate.py
judge_llm/core/models.py
judge_llm/core/registry.py
judge_llm/evaluators/__init__.py
judge_llm/evaluators/base.py
judge_llm/evaluators/cost_evaluator.py
judge_llm/evaluators/embedding_similarity_evaluator.py
judge_llm/evaluators/latency_evaluator.py
judge_llm/evaluators/llm_judge_evaluator.py
judge_llm/evaluators/response_evaluator.py
judge_llm/evaluators/subagent_evaluator.py
judge_llm/evaluators/trajectory_evaluator.py
judge_llm/loaders/__init__.py
judge_llm/loaders/base.py
judge_llm/loaders/directory_loader.py
judge_llm/loaders/local_file_loader.py
judge_llm/providers/__init__.py
judge_llm/providers/adk_http_provider.py
judge_llm/providers/adk_provider.py
judge_llm/providers/base.py
judge_llm/providers/gemini_provider.py
judge_llm/providers/mock_provider.py
judge_llm/providers/adk_http/__init__.py
judge_llm/providers/adk_http/event_mapper.py
judge_llm/providers/adk_http/models.py
judge_llm/providers/adk_http/pricing.py
judge_llm/providers/adk_http/session_manager.py
judge_llm/providers/adk_http/sse_parser.py
judge_llm/reporters/__init__.py
judge_llm/reporters/base.py
judge_llm/reporters/console_reporter.py
judge_llm/reporters/database_reporter.py
judge_llm/reporters/html_reporter.py
judge_llm/reporters/json_reporter.py
judge_llm/templates/monitor.html
judge_llm/templates/report.html
judge_llm/utils/__init__.py
judge_llm/utils/logger.py
judge_llm-1.0.5.dist-info/licenses/LICENSE
judge_llm-1.0.5.dist-info/METADATA
judge_llm-1.0.5.dist-info/WHEEL
judge_llm-1.0.5.dist-info/entry_points.txt
judge_llm-1.0.5.dist-info/top_level.txt
judge_llm-1.0.5.dist-info/RECORD
