Metadata-Version: 2.4
Name: judge-llm
Version: 1.0.5
Summary: A lightweight LLM evaluation framework for comparing and testing AI providers
Author-email: Ilayanambi <hihelloai@yahoo.com>
License: CC-BY-NC-SA-4.0
Project-URL: Homepage, https://github.com/HiHelloAI/judge-llm
Project-URL: Documentation, https://github.com/HiHelloAI/judge-llm#readme
Project-URL: Repository, https://github.com/HiHelloAI/judge-llm
Project-URL: Issues, https://github.com/HiHelloAI/judge-llm/issues
Keywords: llm,evaluation,testing,ai,gemini,openai,claude
Classifier: Development Status :: 3 - Alpha
Classifier: Intended Audience :: Developers
Classifier: License :: Other/Proprietary License
Classifier: Programming Language :: Python :: 3
Classifier: Programming Language :: Python :: 3.9
Classifier: Programming Language :: Python :: 3.10
Classifier: Programming Language :: Python :: 3.11
Classifier: Programming Language :: Python :: 3.12
Classifier: Topic :: Software Development :: Testing
Classifier: Topic :: Scientific/Engineering :: Artificial Intelligence
Requires-Python: >=3.9
License-File: LICENSE
Requires-Dist: pydantic>=2.0.0
Requires-Dist: pyyaml>=6.0
Requires-Dist: jinja2>=3.1.0
Requires-Dist: click>=8.1.0
Requires-Dist: httpx>=0.25.0
Requires-Dist: rich>=13.0.0
Requires-Dist: python-dotenv>=1.0.0
Requires-Dist: dotenv>=0.9.9
Provides-Extra: dev
Requires-Dist: pytest>=7.0.0; extra == "dev"
Requires-Dist: pytest-asyncio>=0.21.0; extra == "dev"
Requires-Dist: pytest-cov>=4.0.0; extra == "dev"
Requires-Dist: black>=23.0.0; extra == "dev"
Requires-Dist: ruff>=0.1.0; extra == "dev"
Provides-Extra: google-adk
Requires-Dist: google-adk==1.16.0; extra == "google-adk"
Requires-Dist: google-adk[eval]==1.16.0; extra == "google-adk"
Requires-Dist: rouge-score; extra == "google-adk"
Provides-Extra: gemini
Requires-Dist: google-genai>=0.1.0; extra == "gemini"
Provides-Extra: openai
Requires-Dist: openai>=1.0.0; extra == "openai"
Provides-Extra: anthropic
Requires-Dist: anthropic>=0.7.0; extra == "anthropic"
Provides-Extra: all
Requires-Dist: google-genai>=0.1.0; extra == "all"
Requires-Dist: openai>=1.0.0; extra == "all"
Requires-Dist: anthropic>=0.7.0; extra == "all"
Dynamic: license-file
